{"HISTORY":{"par":["LVFAILURE"],"nei":[]},"CVP":{"par":["PCWP","LVEDVOLUME"],"nei":[]},"PCWP":{"par":[],"nei":[]},"HYPOVOLEMIA":{"par":["LVEDVOLUME","STROKEVOLUME"],"nei":[]},"LVEDVOLUME":{"par":["PCWP"],"nei":[]},"LVFAILURE":{"par":["PCWP","LVEDVOLUME"],"nei":[]},"STROKEVOLUME":{"par":["LVEDVOLUME","LVFAILURE"],"nei":[]},"ERRLOWOUTPUT":{"par":["HRBP"],"nei":[]},"HRBP":{"par":["ARTCO2"],"nei":[]},"HREKG":{"par":["ERRCAUTER","HR"],"nei":[]},"ERRCAUTER":{"par":[],"nei":[]},"HRSAT":{"par":["HREKG","ERRCAUTER","HR"],"nei":[]},"INSUFFANESTH":{"par":[],"nei":[]},"ANAPHYLAXIS":{"par":["LVFAILURE"],"nei":[]},"TPR":{"par":["SAO2","CATECHOL"],"nei":[]},"EXPCO2":{"par":["VENTLUNG","ARTCO2"],"nei":[]},"KINKEDTUBE":{"par":["PRESS"],"nei":[]},"MINVOL":{"par":["VENTTUBE"],"nei":[]},"FIO2":{"par":[],"nei":[]},"PVSAT":{"par":["FIO2","VENTALV"],"nei":[]},"SAO2":{"par":["PVSAT","SHUNT","VENTALV"],"nei":[]},"PAP":{"par":["SHUNT"],"nei":[]},"PULMEMBOLUS":{"par":["PAP","SHUNT"],"nei":[]},"SHUNT":{"par":["INTUBATION","VENTALV"],"nei":[]},"INTUBATION":{"par":["MINVOL","VENTALV"],"nei":[]},"PRESS":{"par":["INTUBATION","VENTTUBE"],"nei":[]},"DISCONNECT":{"par":[],"nei":[]},"MINVOLSET":{"par":[],"nei":[]},"VENTMACH":{"par":["MINVOLSET"],"nei":[]},"VENTTUBE":{"par":["DISCONNECT","VENTMACH"],"nei":[]},"VENTLUNG":{"par":["MINVOL","INTUBATION","VENTALV"],"nei":[]},"VENTALV":{"par":["MINVOL","VENTTUBE"],"nei":[]},"ARTCO2":{"par":["PVSAT","VENTALV"],"nei":[]},"CATECHOL":{"par":["ARTCO2","HR"],"nei":[]},"HR":{"par":["ERRLOWOUTPUT","HRBP"],"nei":[]},"CO":{"par":["STROKEVOLUME","HR"],"nei":[]},"BP":{"par":["TPR","CO"],"nei":[]}}
