{"HISTORY": {"par": ["LVFAILURE"], "nei": []}, "CVP": {"par": ["LVEDVOLUME"], "nei": []}, "PCWP": {"par": ["LVEDVOLUME"], "nei": []}, "HYPOVOLEMIA": {"par": ["LVEDVOLUME"], "nei": []}, "LVEDVOLUME": {"par": ["STROKEVOLUME"], "nei": ["LVFAILURE"]}, "LVFAILURE": {"par": [], "nei": ["LVEDVOLUME"]}, "STROKEVOLUME": {"par": ["CO"], "nei": []}, "ERRLOWOUTPUT": {"par": ["HRBP"], "nei": []}, "HRBP": {"par": ["HR"], "nei": []}, "HREKG": {"par": ["HRSAT"], "nei": []}, "ERRCAUTER": {"par": [], "nei": []}, "HRSAT": {"par": ["ERRCAUTER", "HR"], "nei": []}, "INSUFFANESTH": {"par": ["ERRLOWOUTPUT"], "nei": []}, "ANAPHYLAXIS": {"par": [], "nei": []}, "TPR": {"par": [], "nei": []}, "EXPCO2": {"par": [], "nei": ["VENTLUNG"]}, "KINKEDTUBE": {"par": [], "nei": ["PRESS"]}, "MINVOL": {"par": [], "nei": ["VENTALV", "VENTTUBE", "VENTLUNG"]}, "FIO2": {"par": [], "nei": []}, "PVSAT": {"par": [], "nei": ["VENTALV", "SAO2"]}, "SAO2": {"par": [], "nei": ["PVSAT"]}, "PAP": {"par": [], "nei": []}, "PULMEMBOLUS": {"par": ["HYPOVOLEMIA"], "nei": []}, "SHUNT": {"par": [], "nei": ["INTUBATION"]}, "INTUBATION": {"par": [], "nei": ["SHUNT", "VENTALV"]}, "PRESS": {"par": [], "nei": ["KINKEDTUBE", "VENTTUBE"]}, "DISCONNECT": {"par": [], "nei": ["VENTTUBE"]}, "MINVOLSET": {"par": [], "nei": ["VENTMACH"]}, "VENTMACH": {"par": [], "nei": ["MINVOLSET", "VENTTUBE"]}, "VENTTUBE": {"par": [], "nei": ["PRESS", "DISCONNECT", "VENTMACH", "MINVOL"]}, "VENTLUNG": {"par": [], "nei": ["EXPCO2", "MINVOL"]}, "VENTALV": {"par": [], "nei": ["MINVOL", "PVSAT", "INTUBATION", "ARTCO2"]}, "ARTCO2": {"par": [], "nei": ["VENTALV"]}, "CATECHOL": {"par": ["ARTCO2", "TPR"], "nei": []}, "HR": {"par": ["CATECHOL"], "nei": []}, "CO": {"par": ["HR"], "nei": []}, "BP": {"par": ["CO", "TPR"], "nei": []}}